possible_words/__init__.py
possible_english_words-0.0.1.dist-info/LICENSE.txt
possible_english_words-0.0.1.dist-info/METADATA
possible_english_words-0.0.1.dist-info/WHEEL
possible_english_words-0.0.1.dist-info/top_level.txt
possible_english_words-0.0.1.dist-info/RECORD
